break_my_python.pth
break_my_python.py
break_my_python-0.0.2.dist-info/DESCRIPTION.rst
break_my_python-0.0.2.dist-info/LICENSE.txt
break_my_python-0.0.2.dist-info/METADATA
break_my_python-0.0.2.dist-info/RECORD
break_my_python-0.0.2.dist-info/WHEEL
break_my_python-0.0.2.dist-info/metadata.json
break_my_python-0.0.2.dist-info/top_level.txt
